amazon_mws_lib/__init__.py
amazon_mws_lib/create_shipment_request.py
amazon_mws_lib/create_shipment_response.py
amazon_mws_lib/error_response.py
amazon_mws_lib/purchase_label_request.py
amazon_mws_lib/purchase_label_response.py
amazon_mws_lib/purchase_shipment_request.py
amazon_mws_lib/purchase_shipment_response.py
amazon_mws_lib/rate_request.py
amazon_mws_lib/rate_response.py
amazon_mws_lib/shipping_label.py
amazon_mws_lib/tracking_response.py
karrio/mappers/amazon_mws/__init__.py
karrio/mappers/amazon_mws/mapper.py
karrio/mappers/amazon_mws/proxy.py
karrio/mappers/amazon_mws/settings.py
karrio/providers/amazon_mws/__init__.py
karrio/providers/amazon_mws/error.py
karrio/providers/amazon_mws/rate.py
karrio/providers/amazon_mws/tracking.py
karrio/providers/amazon_mws/units.py
karrio/providers/amazon_mws/utils.py
karrio/providers/amazon_mws/shipment/__init__.py
karrio/providers/amazon_mws/shipment/cancel.py
karrio/providers/amazon_mws/shipment/create.py
karrio.amazon_mws-2023.4.4.dist-info/LICENSE
karrio.amazon_mws-2023.4.4.dist-info/METADATA
karrio.amazon_mws-2023.4.4.dist-info/WHEEL
karrio.amazon_mws-2023.4.4.dist-info/top_level.txt
karrio.amazon_mws-2023.4.4.dist-info/RECORD
