Metadata-Version: 2.1
Name: karrio.amazon-mws
Version: 2023.4.4
Summary: Karrio - AmazonMws Shipping extension
Home-page: https://github.com/karrioapi/karrio
Author: karrio
Author-email: hello@karrio.io
License: Apache-2.0
Platform: UNKNOWN
Classifier: Intended Audience :: Developers
Classifier: Operating System :: OS Independent
Classifier: Programming Language :: Python :: 3
License-File: LICENSE
Requires-Dist: karrio
